fastrtps/_dummy.cpython-312-x86_64-linux-gnu.so
ros_fastrtps-2.14.5.data/data/bin/fast-discovery-server
ros_fastrtps-2.14.5.data/data/bin/fast-discovery-server-1.0.1
ros_fastrtps-2.14.5.data/data/bin/fastdds
ros_fastrtps-2.14.5.data/data/bin/ros-discovery
ros_fastrtps-2.14.5.data/data/include/fastdds/dds/builtin/common/ReplyHeader.hpp
ros_fastrtps-2.14.5.data/data/include/fastdds/dds/builtin/common/RequestHeader.hpp
ros_fastrtps-2.14.5.data/data/include/fastdds/dds/builtin/common/Types.hpp
ros_fastrtps-2.14.5.data/data/include/fastdds/dds/builtin/topic/BuiltinTopicKey.hpp
ros_fastrtps-2.14.5.data/data/include/fastdds/dds/builtin/topic/ParticipantBuiltinTopicData.hpp
ros_fastrtps-2.14.5.data/data/include/fastdds/dds/builtin/topic/PublicationBuiltinTopicData.hpp
ros_fastrtps-2.14.5.data/data/include/fastdds/dds/builtin/topic/SubscriptionBuiltinTopicData.hpp
ros_fastrtps-2.14.5.data/data/include/fastdds/dds/builtin/topic/TopicBuiltinTopicData.hpp
ros_fastrtps-2.14.5.data/data/include/fastdds/dds/builtin/typelookup/TypeLookupManager.hpp
ros_fastrtps-2.14.5.data/data/include/fastdds/dds/builtin/typelookup/TypeLookupReplyListener.hpp
ros_fastrtps-2.14.5.data/data/include/fastdds/dds/builtin/typelookup/TypeLookupRequestListener.hpp
ros_fastrtps-2.14.5.data/data/include/fastdds/dds/builtin/typelookup/common/TypeLookupTypes.hpp
ros_fastrtps-2.14.5.data/data/include/fastdds/dds/common/InstanceHandle.hpp
ros_fastrtps-2.14.5.data/data/include/fastdds/dds/core/Entity.hpp
ros_fastrtps-2.14.5.data/data/include/fastdds/dds/core/LoanableArray.hpp
ros_fastrtps-2.14.5.data/data/include/fastdds/dds/core/LoanableCollection.hpp
ros_fastrtps-2.14.5.data/data/include/fastdds/dds/core/LoanableSequence.hpp
ros_fastrtps-2.14.5.data/data/include/fastdds/dds/core/LoanableTypedCollection.hpp
ros_fastrtps-2.14.5.data/data/include/fastdds/dds/core/StackAllocatedSequence.hpp
ros_fastrtps-2.14.5.data/data/include/fastdds/dds/core/UserAllocatedSequence.hpp
ros_fastrtps-2.14.5.dist-info/METADATA
ros_fastrtps-2.14.5.dist-info/WHEEL
ros_fastrtps-2.14.5.dist-info/top_level.txt
ros_fastrtps-2.14.5.dist-info/RECORD
ros_fastrtps-2.14.5.dist-info/licenses/LICENSE
