Metadata-Version: 2.4
Name: ros-fastrtps
Version: 2.14.5
Summary: ROS package for eProsima Fast DDS, a high-performance Data Distribution Service (DDS) middleware for real-time robotics communication.
License-File: LICENSE
Requires-Dist: ros-fastcdr~=2.2.5
Requires-Dist: ros-foonathan-memory-vendor~=1.3.1
Dynamic: description
Dynamic: description-content-type
Dynamic: license-file
Dynamic: requires-dist
Dynamic: summary
